odoo/addons/account_peppol_partner/README.rst
odoo/addons/account_peppol_partner/__init__.py
odoo/addons/account_peppol_partner/__manifest__.py
odoo/addons/account_peppol_partner/models/__init__.py
odoo/addons/account_peppol_partner/models/eas_mapping.py
odoo/addons/account_peppol_partner/models/res_partner.py
odoo/addons/account_peppol_partner/readme/CONTRIBUTORS.md
odoo/addons/account_peppol_partner/readme/CREDITS.md
odoo/addons/account_peppol_partner/readme/DESCRIPTION.md
odoo/addons/account_peppol_partner/static/description/index.html
odoo/addons/account_peppol_partner/tests/__init__.py
odoo/addons/account_peppol_partner/tests/test_partner_peppol_fields.py
odoo/addons/account_peppol_partner/views/res_partner_views.xml
odoo_addon_account_peppol_partner-16.0.1.0.0.1.dist-info/METADATA
odoo_addon_account_peppol_partner-16.0.1.0.0.1.dist-info/WHEEL
odoo_addon_account_peppol_partner-16.0.1.0.0.1.dist-info/top_level.txt
odoo_addon_account_peppol_partner-16.0.1.0.0.1.dist-info/RECORD
